Metadata-Version: 2.1
Name: appsec-utils
Version: 1.99.106
Summary: This package is supposed to demostrate the effects of a Dependency Confusion attack
Home-page: https://medium.com/@alex.birsan/dependency-confusion-4a5d60fec610
Author: Appsec@SBB
Author-email: application-security@sbb.ch
License: UNKNOWN
Platform: UNKNOWN
Classifier: Development Status :: 4 - Beta
Classifier: Intended Audience :: Developers
Classifier: Programming Language :: Python :: 3.10
Requires-Python: >=3.10
